{
  "type": "FeatureCollection",
  "crs": { "type": "name", "properties": { "name": "urn:ogc:def:crs:OGC:1.3:CRS84" } },
  "features": [
    {
      "type": "Feature",
      "properties": { "Name": "Brew by Numbers", "marker-symbol": "beer", "open hours": "11am-6pm" },
      "geometry": { "type": "Point", "coordinates": [ -0.071998, 51.497437, 0.0 ] }
    },
    {
      "type": "Feature",
      "properties": { "Name": "Kernel", "marker-symbol": "beer", "open hours": "9am-3pm" },
      "geometry": { "type": "Point", "coordinates": [ -0.068553, 51.495682, 0.0 ] }
    },
    {
      "type": "Feature",
      "properties": { "Name": "Partizan", "marker-symbol": "beer", "open hours": "11am-5pm" },
      "geometry": { "type": "Point", "coordinates": [ -0.059559, 51.49173, 0.0 ] }
    },
    {
      "type": "Feature",
      "properties": { "Name": "Fourpure", "marker-symbol": "beer", "open hours": "11am-5pm" },
      "geometry": { "type": "Point", "coordinates": [ -0.054041147232055664, 51.489239763634764, 0.0 ] }
    }
    ,
  ]
}
