{
  "type": "FeatureCollection",
  "crs": { "type": "name", "properties": { "name": "urn:ogc:def:crs:OGC:1.3:CRS84" } },
  "features": [
    {
      "type": "Feature",
      "properties": { "Name": "Brew by Numbers", "marker-symbol": "beer" },
      "geometry": { "type": "Point", "coordinates": [ -0.071998, 51.497437, 0.0 ] }
    },
    {
      "type": "Feature",
      "properties": { "Name": "Kernel", "marker-symbol": "beer" },
      "geometry": { "type": "Point", "coordinates": [ -0.068553, 51.495682, 0.0 ] }
    },
    {
      "type": "Feature",
      "properties": { "Name": "Partizan", "marker-symbol": "beer" },
      "geometry": { "type": "Point", "coordinates": [ -0.059559, 51.49173, 0.0 ] }
    }
  ]
}
